pyagrum-2.3.2.dist-info/LICENSE.md
pyagrum-2.3.2.dist-info/WHEEL
pyagrum-2.3.2.dist-info/METADATA
pyagrum-2.3.2.dist-info/LICENSES/LGPL-3.0-or-later.txt
pyagrum-2.3.2.dist-info/LICENSES/MIT.txt
pyagrum/defaults.ini
pyagrum/config.py
pyagrum/deprecated.py
pyagrum/__init__.py
pyagrum/_pyagrum.so
pyagrum/common.py
pyagrum/pyagrum.py
pyagrum/ctbn/CTBNLearner.py
pyagrum/ctbn/constants.py
pyagrum/ctbn/__init__.py
pyagrum/ctbn/SamplesStats.py
pyagrum/ctbn/StatsIndepTest.py
pyagrum/ctbn/CIM.py
pyagrum/ctbn/CTBNGenerator.py
pyagrum/ctbn/notebook.py
pyagrum/ctbn/CTBN.py
pyagrum/ctbn/CTBNInference.py
pyagrum/explain/_explIndependenceListForPairs.py
pyagrum/explain/_ComputationMarginal.py
pyagrum/explain/_ShallCausalValues.py
pyagrum/explain/_ShallMarginalValues.py
pyagrum/explain/_CustomShapleyCache.py
pyagrum/explain/_ShapConditionalValues.py
pyagrum/explain/_explGeneralizedMarkovBlanket.py
pyagrum/explain/__init__.py
pyagrum/explain/_ShallConditionalValues.py
pyagrum/explain/_Explainer.py
pyagrum/explain/_Explanation.py
pyagrum/explain/_ShallValues.py
pyagrum/explain/_ComputationCausal.py
pyagrum/explain/_explInformationGraph.py
pyagrum/explain/_FIFOCache.py
pyagrum/explain/_ShapMarginalValues.py
pyagrum/explain/_ShapCausalValues.py
pyagrum/explain/shapley.py
pyagrum/explain/_ShapleyValues.py
pyagrum/explain/_ComputationConditional.py
pyagrum/explain/notebook/__init__.py
pyagrum/explain/notebook/_beeswarm.py
pyagrum/explain/notebook/_bar.py
pyagrum/explain/notebook/_showShapValues.py
pyagrum/explain/notebook/_waterfall.py
pyagrum/causal/_types.py
pyagrum/causal/_dSeparation.py
pyagrum/causal/_causalImpact.py
pyagrum/causal/__init__.py
pyagrum/causal/_CausalFormula.py
pyagrum/causal/_doorCriteria.py
pyagrum/causal/_doAST.py
pyagrum/causal/notebook.py
pyagrum/causal/_exceptions.py
pyagrum/causal/_CausalModel.py
pyagrum/causal/_doCalculus.py
pyagrum/causal/causalEffectEstimation/_causalBNEstimator.py
pyagrum/causal/causalEffectEstimation/__init__.py
pyagrum/causal/causalEffectEstimation/_frontdoorEstimators.py
pyagrum/causal/causalEffectEstimation/_RCTEstimators.py
pyagrum/causal/causalEffectEstimation/_learners.py
pyagrum-2.3.2.dist-info/RECORD