Metadata-Version: 2.4
Name: pyAgrum
Version: 2.3.2
Summary: Bayesian networks and other Probabilistic Graphical Models.
Home-page: https://agrum.gitlab.io/
Author: Pierre-Henri Wuillemin and Christophe Gonzales
Author-email: info@agrum.org
License-Expression: LGPL-3.0-only OR MIT
Keywords: probabilities probabilistic-graphical-models inference diagnosis
Project-URL: Bug Tracker, https://gitlab.com/agrumery/aGrUM/-/issues
Project-URL: Documentation, https://pyagrum.readthedocs.io/
Project-URL: Source Code, https://gitlab.com/agrumery/aGrUM
Platform: any
Classifier: Development Status :: 5 - Production/Stable
Classifier: License :: OSI Approved :: MIT License
Classifier: License :: OSI Approved :: GNU Lesser General Public License v3 (LGPLv3)
Classifier: Operating System :: Microsoft :: Windows
Classifier: Operating System :: MacOS :: MacOS X
Classifier: Operating System :: POSIX :: Linux
Classifier: Programming Language :: C++
Classifier: Programming Language :: Python
Classifier: Programming Language :: Python :: 3
Classifier: Programming Language :: Python :: 3.10
Classifier: Programming Language :: Python :: 3.11
Classifier: Programming Language :: Python :: 3.12
Classifier: Programming Language :: Python :: 3.13
Classifier: Programming Language :: Python :: 3.14
Classifier: Topic :: Scientific/Engineering :: Artificial Intelligence
Classifier: Topic :: Scientific/Engineering :: Information Analysis
Classifier: Topic :: Scientific/Engineering :: Mathematics
Classifier: Topic :: Software Development :: Libraries
Classifier: Topic :: Software Development :: Libraries :: Python Modules
Classifier: Intended Audience :: Developers
Classifier: Intended Audience :: Financial and Insurance Industry
Classifier: Intended Audience :: Information Technology
Classifier: Intended Audience :: Science/Research
Requires-Python: >=3.10
Requires-Dist: numpy
Requires-Dist: matplotlib
Requires-Dist: pydot
Requires-Dist: scikit-learn >= 1.7
